tokflow/__init__.py
tokflow/sentence_stop.py
tokflow/tok_flow.py
tokflow/tok_flow_worker.py
tokflow-1.3.1.dist-info/LICENSE
tokflow-1.3.1.dist-info/METADATA
tokflow-1.3.1.dist-info/WHEEL
tokflow-1.3.1.dist-info/top_level.txt
tokflow-1.3.1.dist-info/RECORD
