Metadata-Version: 2.1
Name: tokflow
Version: 1.3.1
Summary: LLM utility of streaming token realtime replacement processing
Home-page: https://github.com/riversun/TokFlow
Author: Tom Misawa
Author-email: riversun.org@gmail.com
License: GPLv3 or Commercial
Classifier: Development Status :: 5 - Production/Stable
Classifier: Intended Audience :: Developers
Classifier: License :: OSI Approved :: GNU General Public License v3 (GPLv3)
Classifier: Programming Language :: Python :: 3.8
Classifier: Programming Language :: Python :: 3.9
Classifier: Programming Language :: Python :: 3.10
Requires-Python: >=3.8
License-File: LICENSE
